__init_.py
num2devanagari.py
num2devanagari-0.22.0.dist-info/LICENSE
num2devanagari-0.22.0.dist-info/METADATA
num2devanagari-0.22.0.dist-info/WHEEL
num2devanagari-0.22.0.dist-info/top_level.txt
num2devanagari-0.22.0.dist-info/RECORD
