Metadata-Version: 2.1
Name: num2devanagari
Version: 0.22.0
Summary: A simple python library for converting integers to their corresponding Devanagari word representations.
Author-email: Aananda Giri <aanandaprashadgiri@gmail.com>
Project-URL: Homepage, https://github.com/Aananda-giri/Num2Devanagari
Project-URL: Issues, https://github.com/Aananda-giri/Num2Devanagari/issues
Classifier: Programming Language :: Python :: 3
Classifier: License :: OSI Approved :: MIT License
Classifier: Operating System :: OS Independent
Requires-Python: >=3.8
License-File: LICENSE
